mkdocs_image_localization/__init__.py
mkdocs_image_localization/plugin.py
mkdocs_image_localization-0.1.8.dist-info/LICENSE
mkdocs_image_localization-0.1.8.dist-info/METADATA
mkdocs_image_localization-0.1.8.dist-info/WHEEL
mkdocs_image_localization-0.1.8.dist-info/entry_points.txt
mkdocs_image_localization-0.1.8.dist-info/top_level.txt
mkdocs_image_localization-0.1.8.dist-info/RECORD
